main.py
mcp_server_demo2-0.1.0.dist-info/METADATA
mcp_server_demo2-0.1.0.dist-info/WHEEL
mcp_server_demo2-0.1.0.dist-info/top_level.txt
mcp_server_demo2-0.1.0.dist-info/RECORD
